qualia_plugin_template-2.3.0.dist-info/METADATA
qualia_plugin_template-2.3.0.dist-info/WHEEL
qualia_plugin_template-2.3.0.dist-info/entry_points.txt
qualia_plugin_template-2.3.0.dist-info/licenses/LICENSE
qualia_plugin_template/__init__.py
qualia_plugin_template/assets/__init__.py
qualia_plugin_template/assets/template/.copier-answers.yml.jinja
qualia_plugin_template/assets/template/.editorconfig
qualia_plugin_template/assets/template/.gitignore
qualia_plugin_template/assets/template/.gitlab-ci.yml
qualia_plugin_template/assets/template/LICENSE.jinja
qualia_plugin_template/assets/template/README.md.jinja
qualia_plugin_template/assets/template/conf/dummy/Dummy.toml.jinja
qualia_plugin_template/assets/template/copier.yml
qualia_plugin_template/assets/template/docs/.gitignore
qualia_plugin_template/assets/template/docs/Makefile
qualia_plugin_template/assets/template/docs/conf.py.jinja
qualia_plugin_template/assets/template/docs/index.rst.jinja
qualia_plugin_template/assets/template/input.yml
qualia_plugin_template/assets/template/pyproject.toml.jinja
qualia_plugin_template/assets/template/src/.gitlab-ci.yml.jinja
qualia_plugin_template/assets/template/src/{{python_module_name}}/__init__.py.jinja
qualia_plugin_template/assets/template/src/{{python_module_name}}/dataset/Dummy.py
qualia_plugin_template/assets/template/src/{{python_module_name}}/dataset/__init__.py.jinja
qualia_plugin_template/assets/template/src/{{python_module_name}}/learningframework/PyTorch.py.jinja
qualia_plugin_template/assets/template/src/{{python_module_name}}/learningframework/__init__.py.jinja
qualia_plugin_template/assets/template/src/{{python_module_name}}/learningmodel/__init__.py.jinja
qualia_plugin_template/assets/template/src/{{python_module_name}}/learningmodel/pytorch/Dummy.py
qualia_plugin_template/assets/template/src/{{python_module_name}}/learningmodel/pytorch/__init__.py
qualia_plugin_template/assets/template/src/{{python_module_name}}/postprocessing/Dummy.py
qualia_plugin_template/assets/template/src/{{python_module_name}}/postprocessing/__init__.py.jinja
qualia_plugin_template/assets/template/src/{{python_module_name}}/preprocessing/Dummy.py
qualia_plugin_template-2.3.0.dist-info/RECORD
