Metadata-Version: 2.1
Name: qualia-plugin-template
Version: 2.3.0
Summary: Qualia Plugin Template
Home-page: https://github.com/LEAT-EDGE/qualia-plugin-template
Author-Email: Pierre-Emmanuel Novac <penovac@unice.fr>
License: AGPL-3.0-or-later
Classifier: Programming Language :: Python :: 3
Classifier: License :: OSI Approved :: GNU Affero General Public License v3
Classifier: Operating System :: OS Independent
Project-URL: Homepage, https://github.com/LEAT-EDGE/qualia-plugin-template
Project-URL: Documentation, https://leat-edge.github.io/qualia-plugin-template
Requires-Python: <3.13,>=3.9
Requires-Dist: qualia_core
Requires-Dist: copier
Requires-Dist: gitpython
Requires-Dist: ruff; extra == "lint"
Requires-Dist: mypy; extra == "typecheck"
Requires-Dist: pyright; extra == "typecheck"
Requires-Dist: pdm; extra == "docs"
Requires-Dist: sphinx; extra == "docs"
Requires-Dist: sphinx-rtd-theme; extra == "docs"
Requires-Dist: myst-parser; extra == "docs"
Provides-Extra: lint
Provides-Extra: typecheck
Provides-Extra: docs
